MANIFEST.in
README.rst
setup.py
pixelfields_smart_selects/__init__.py
pixelfields_smart_selects/db_fields.py
pixelfields_smart_selects/form_fields.py
pixelfields_smart_selects/models.py
pixelfields_smart_selects/urls.py
pixelfields_smart_selects/utils.py
pixelfields_smart_selects/views.py
pixelfields_smart_selects/widgets.py
pixelfields_smart_selects.egg-info/PKG-INFO
pixelfields_smart_selects.egg-info/SOURCES.txt
pixelfields_smart_selects.egg-info/dependency_links.txt
pixelfields_smart_selects.egg-info/requires.txt
pixelfields_smart_selects.egg-info/top_level.txt