Metadata-Version: 1.1
Name: pixelfields-smart-selects
Version: 0.1.5
Summary: Smart selects for Django >= 1.7
Home-page: https://bitbucket.org/pixelfields/smart-selects
Author: pixelfields
Author-email: pixelfields@runbox.com
License: UNKNOWN
Download-URL: https://bitbucket.org/pixelfields/smart-selects/get/v0.1.5.tar.gz
Keywords: django,admin,chained,selects
Platform: UNKNOWN
Classifier: Environment :: Web Environment
Classifier: Framework :: Django
Classifier: Intended Audience :: Developers
Classifier: License :: OSI Approved :: BSD License
Classifier: Operating System :: OS Independent
Classifier: Programming Language :: Python
Classifier: Programming Language :: Python :: 2.6
Classifier: Programming Language :: Python :: 2.7
Classifier: Topic :: Internet :: WWW/HTTP
Classifier: Topic :: Internet :: WWW/HTTP :: Dynamic Content
